simplepipeline/__init__.py
simplepipeline/pipeline.py
simplepipeline/task.py
simplepipeline/map/__init__.py
simplepipeline/map/base_map.py
simplepipeline/map/parallel.py
simplepipeline/map/sequential.py
simplepipeline/utils/__init__.py
simplepipeline/utils/task_logger.py
simplepipeline-0.2.1.dist-info/LICENSE.txt
simplepipeline-0.2.1.dist-info/METADATA
simplepipeline-0.2.1.dist-info/WHEEL
simplepipeline-0.2.1.dist-info/top_level.txt
simplepipeline-0.2.1.dist-info/RECORD
