Metadata-Version: 2.1
Name: simplepipeline
Version: 0.2.1
Summary: UNKNOWN
Home-page: https://github.com/lucasfbn/SimplePipeline
Author: Lucas Fobian
Author-email: UNKNOWN
License: MIT
Platform: UNKNOWN
Classifier: Development Status :: 3 - Alpha
Classifier: Intended Audience :: Developers
Classifier: Topic :: Software Development :: Build Tools
Classifier: License :: OSI Approved :: MIT License
Classifier: Programming Language :: Python :: 3
Requires-Dist: pandas
Requires-Dist: ray
Requires-Dist: tqdm
